{
    "checksum": "bb259ef644054c5621c2734981aee887f08b0818de99fb71f63dd06ab598fa05",
    "file": "Makefile.in",
    "mime": {
        "encoding": "us-ascii",
        "type": "text/x-makefile"
    },
    "number_of_duplicates": 1,
    "package": "alsa-lib",
    "path": "alsa-lib/1.2.5.1-1/utils/Makefile.in",
    "pkg_infos": {
        "area": "main",
        "copyright": true,
        "ctags_count": 0,
        "license": "/copyright/license/alsa-lib/1.2.5.1-1/",
        "metric": {
            "size": 7676
        },
        "pts_link": "https://tracker.debian.org/pkg/alsa-lib",
        "sloc": [
            [
                "ansic",
                95122
            ],
            [
                "sh",
                4387
            ],
            [
                "makefile",
                673
            ]
        ],
        "suites": [
            "bookworm",
            "sid"
        ],
        "vcs_browser": "https://salsa.debian.org/alsa-team/alsa-lib",
        "vcs_type": "git"
    },
    "raw_url": "/data/main/a/alsa-lib/1.2.5.1-1/utils/Makefile.in",
    "stat": {
        "perms": "rw-r--r--",
        "size": 16735,
        "symlink_dest": null,
        "type": "-"
    },
    "text_file": true,
    "type": "file",
    "version": "1.2.5.1-1"
}