{
    "checksum": "b6df2b1986dbc8cc543130f6fe07c58e8c0f96f360891081096df1d3b4bd865f",
    "file": "Echo_Echo3G.conf",
    "mime": {
        "encoding": "us-ascii",
        "type": "text/plain"
    },
    "number_of_duplicates": 5,
    "package": "alsa-lib",
    "path": "alsa-lib/1.2.5.1-1/src/conf/cards/Echo_Echo3G.conf",
    "pkg_infos": {
        "area": "main",
        "copyright": true,
        "ctags_count": 0,
        "license": "/copyright/license/alsa-lib/1.2.5.1-1/",
        "metric": {
            "size": 7676
        },
        "pts_link": "https://tracker.debian.org/pkg/alsa-lib",
        "sloc": [
            [
                "ansic",
                95122
            ],
            [
                "sh",
                4387
            ],
            [
                "makefile",
                673
            ]
        ],
        "suites": [
            "bookworm",
            "sid"
        ],
        "vcs_browser": "https://salsa.debian.org/alsa-team/alsa-lib",
        "vcs_type": "git"
    },
    "raw_url": "/data/main/a/alsa-lib/1.2.5.1-1/src/conf/cards/Echo_Echo3G.conf",
    "stat": {
        "perms": "rw-r--r--",
        "size": 4399,
        "symlink_dest": null,
        "type": "-"
    },
    "text_file": true,
    "type": "file",
    "version": "1.2.5.1-1"
}